pystagram/__init__.py
pystagram/basic_display_api/__init__.py
pystagram/basic_display_api/basic_display_api.py
pystagram/basic_display_api/endpoints/__init__.py
pystagram/basic_display_api/endpoints/access_token/__init__.py
pystagram/basic_display_api/endpoints/access_token/access_token.py
pystagram/basic_display_api/endpoints/media/__init__.py
pystagram/basic_display_api/endpoints/media/children.py
pystagram/basic_display_api/endpoints/media/media.py
pystagram/basic_display_api/endpoints/oauth/__init__.py
pystagram/basic_display_api/endpoints/oauth/oauth.py
pystagram/basic_display_api/endpoints/oauth/access_token/__init__.py
pystagram/basic_display_api/endpoints/oauth/access_token/access_token.py
pystagram/basic_display_api/endpoints/oauth/authorize/__init__.py
pystagram/basic_display_api/endpoints/oauth/authorize/authorize.py
pystagram/basic_display_api/endpoints/refresh_access_token/__init__.py
pystagram/basic_display_api/endpoints/refresh_access_token/refresh_access_token.py
pystagram/basic_display_api/endpoints/user/__init__.py
pystagram/basic_display_api/endpoints/user/user.py
pystagram/basic_display_api/endpoints/user/user_media.py
pystagram/components/__init__.py
pystagram/components/breakdown/__init__.py
pystagram/components/breakdown/breakdown.py
pystagram/components/containers/__init__.py
pystagram/components/containers/base_container.py
pystagram/components/containers/carousel_container.py
pystagram/components/containers/image_container.py
pystagram/components/containers/reel_container.py
pystagram/components/containers/story_container.py
pystagram/components/containers/video_container.py
pystagram/components/fields/__init__.py
pystagram/components/fields/account_fields.py
pystagram/components/fields/base_fields.py
pystagram/components/fields/catalog_fields.py
pystagram/components/fields/comment_fields.py
pystagram/components/fields/container_fields.py
pystagram/components/fields/fields.py
pystagram/components/fields/hashtag_fields.py
pystagram-1.2.0.dist-info/METADATA
pystagram-1.2.0.dist-info/WHEEL
pystagram-1.2.0.dist-info/licenses/LICENSE
pystagram-1.2.0.dist-info/RECORD
