Metadata-Version: 2.3
Name: pystagram
Version: 1.2.0
Summary: API wrapper for Instagram APIs
Project-URL: Homepage, https://github.com/MatthieuThib/pystagram
Project-URL: Source, https://github.com/MatthieuThib/pystagram
Project-URL: Issues, https://github.com/MatthieuThib/pystagram/issues
Project-URL: Documentation, https://pystagram.readthedocs.io/en/latest/
Author-email: Matthieu THIBAUT <matthieu_thibaut@icloud.com>
License: MIT License
License-File: LICENSE
Keywords: api,basic-display-api,facebook,graph-api,instagram,instagram-api,meta,pystagram,wrapper
Classifier: Development Status :: 3 - Alpha
Classifier: Intended Audience :: Science/Research
Classifier: Intended Audience :: Telecommunications Industry
Classifier: License :: OSI Approved :: MIT License
Classifier: Natural Language :: English
Classifier: Operating System :: MacOS :: MacOS X
Classifier: Operating System :: Microsoft :: Windows
Classifier: Operating System :: POSIX
Classifier: Operating System :: Unix
Classifier: Programming Language :: Python :: 3
Classifier: Programming Language :: Python :: 3.8
Classifier: Programming Language :: Python :: 3.9
Classifier: Programming Language :: Python :: 3.10
Classifier: Topic :: Scientific/Engineering
Classifier: Topic :: Scientific/Engineering :: Information Analysis
Classifier: Topic :: Software Development
Classifier: Typing :: Typed
Requires-Python: >=3.8
Requires-Dist: requests
Provides-Extra: dev
Requires-Dist: twine; extra == 'dev'
Provides-Extra: docs
Requires-Dist: sphinx; extra == 'docs'
Requires-Dist: sphinx-rtd-theme; extra == 'docs'
Provides-Extra: test
Requires-Dist: pytest; extra == 'test'
